pip_conf.py
pip_conf_mirror-0.9.0.dist-info/METADATA
pip_conf_mirror-0.9.0.dist-info/WHEEL
pip_conf_mirror-0.9.0.dist-info/entry_points.txt
pip_conf_mirror-0.9.0.dist-info/licenses/LICENSE
pip_conf_mirror-0.9.0.dist-info/RECORD
