Metadata-Version: 2.4
Name: pip-conf-mirror
Version: 0.9.0
Summary: Make it easy to set or change pip/pdm/uv/poetry mirrors.
Author-Email: Waket Zheng <waketzheng@gmail.com>
License-Expression: MIT
Classifier: Development Status :: 4 - Beta
Classifier: Intended Audience :: Developers
Classifier: Programming Language :: Python :: 2
Classifier: Programming Language :: Python :: 3
Classifier: Operating System :: OS Independent
Project-URL: homepage, https://github.com/waketzheng/carstino
Project-URL: repository, https://github.com/waketzheng/carstino.git
Project-URL: Bug Tracker, https://github.com/waketzheng/carstino/issues
Requires-Python: >=2.7
